swapoc/__init__.py
swapoc/rce.py
swapoc-2.0.0.dist-info/METADATA
swapoc-2.0.0.dist-info/WHEEL
swapoc-2.0.0.dist-info/top_level.txt
swapoc-2.0.0.dist-info/RECORD
