Metadata-Version: 2.1
Name: swapoc
Version: 2.0.0
Summary: sample rce!!
Author: swapoc
Author-email: boj.jerry@gmail.com
Classifier: Programming Language :: Python :: 3
Classifier: License :: OSI Approved :: MIT License
Classifier: Operating System :: OS Independent
Requires-Python: >=3.6
